{
  "saleValueM": null,
  "lng": -122.2008,
  "highlightsEn": [
    "Bellevue office",
    "Commercial"
  ],
  "bodyEn": "Office asset in Bellevue held within the Global Land commercial portfolio.",
  "slug": "belleview-officeTEST",
  "highlightsZh": [
    "贝尔维尤办公",
    "商业"
  ],
  "featured": false,
  "published": true,
  "summaryEn": "Office asset in Bellevue held within the Global Land commercial portfolio.",
  "units": null,
  "bodyZh": "Global Land 商业组合中的贝尔维尤办公资产。",
  "bodyFont": "body",
  "acquisitionPriceM": null,
  "status": "acquired",
  "nameEn": "Belleview Office",
  "summaryZh": "Global Land 商业组合中的贝尔维尤办公资产。",
  "cityEn": "Bellevue",
  "cityZh": "贝尔维尤",
  "nameZh": "Belleview 办公楼",
  "type": "office",
  "id": "belleview-office",
  "image": "/images/projects/belleview-office.png",
  "year": 2023,
  "buildings": 1,
  "lat": 47.6105
}
